<?xml version="1.0" encoding="utf-8" ?>
<dwsync>
<file name="img_list_seiryu01_thumb.jpg" server="ftp-ario-net.heteml.net//web/h-kyocera/" local="132525805790000000" remote="132528258000000000" Dst="0" />
<file name="img_list_seiryu01_thumb@2x.jpg" server="ftp-ario-net.heteml.net//web/h-kyocera/" local="132525805800000000" remote="132528258000000000" Dst="0" />
<file name="img_list_seiryu01.jpg" server="ftp-ario-net.heteml.net//web/h-kyocera/" local="132525805700000000" remote="132528258000000000" Dst="0" />
<file name="img_list_seiryu02.jpg" server="ftp-ario-net.heteml.net//web/h-kyocera/" local="132525805820000000" remote="132528258000000000" Dst="0" />
<file name="img_list_seiryu01@2x.jpg" server="ftp-ario-net.heteml.net//web/h-kyocera/" local="132525805770000000" remote="132528258000000000" Dst="0" />
<file name="img_list_seiryu02_thumb.jpg" server="ftp-ario-net.heteml.net//web/h-kyocera/" local="132525805850000000" remote="132528258000000000" Dst="0" />
<file name="img_list_seiryu02@2x.jpg" server="ftp-ario-net.heteml.net//web/h-kyocera/" local="132525805850000000" remote="132528258000000000" Dst="0" />
<file name="img_list_seiryu02_thumb@2x.jpg" server="ftp-ario-net.heteml.net//web/h-kyocera/" local="132525805860000000" remote="132528258000000000" Dst="0" />
<file name="img_seiryu01.jpg" server="ftp-ario-net.heteml.net//web/h-kyocera/" local="132525805890000000" remote="132528258000000000" Dst="0" />
<file name="img_seiryu02.jpg" server="ftp-ario-net.heteml.net//web/h-kyocera/" local="132525805940000000" remote="132528258000000000" Dst="0" />
<file name="img_seiryu02@2x.jpg" server="ftp-ario-net.heteml.net//web/h-kyocera/" local="132525805970000000" remote="132528258000000000" Dst="0" />
<file name="img_seiryu01@2x.jpg" server="ftp-ario-net.heteml.net//web/h-kyocera/" local="132525805920000000" remote="132528258000000000" Dst="0" />
<file name="lkv_img_seiryu.jpg" server="ftp-ario-net.heteml.net//web/h-kyocera/" local="132523161278065245" remote="132528258000000000" Dst="0" />
<file name="lkv_img_seiryu@2x.jpg" server="ftp-ario-net.heteml.net//web/h-kyocera/" local="132523161295430949" remote="132528258000000000" Dst="0" />
</dwsync>